[
    {
        "key": "dbln",
        "value": "%7B%2261566637599017%22%3A%22FLT6I60S%22%2C%2261563938184202%22%3A%228jgzdXoo%22%7D",
        "domain": "facebook.com",
        "path": "/login/device-based/",
        "hostOnly": false,
        "creation": "2024-10-08T03:03:11.860Z",
        "lastAccessed": "2024-10-08T03:03:11.861Z"
    },
    {
        "key": "datr",
        "value": "4OgDZw8F5pnFDbXPjbPAmJYe",
        "domain": "facebook.com",
        "path": "/",
        "hostOnly": false,
        "creation": "2024-10-08T03:03:11.861Z",
        "lastAccessed": "2024-10-08T03:03:11.861Z"
    },
    {
        "key": "sb",
        "value": "4OgDZ8O-JJ2FLsAYU47Zi5Zi",
        "domain": "facebook.com",
        "path": "/",
        "hostOnly": false,
        "creation": "2024-10-08T03:03:11.861Z",
        "lastAccessed": "2024-10-08T03:03:11.861Z"
    },
    {
        "key": "ps_l",
        "value": "1",
        "domain": "facebook.com",
        "path": "/",
        "hostOnly": false,
        "creation": "2024-10-08T03:03:11.861Z",
        "lastAccessed": "2024-10-08T03:03:11.861Z"
    },
    {
        "key": "ps_n",
        "value": "1",
        "domain": "facebook.com",
        "path": "/",
        "hostOnly": false,
        "creation": "2024-10-08T03:03:11.861Z",
        "lastAccessed": "2024-10-08T03:03:11.861Z"
    },
    {
        "key": "vpd",
        "value": "v1%3B694x360x2",
        "domain": "facebook.com",
        "path": "/",
        "hostOnly": false,
        "creation": "2024-10-08T03:03:11.861Z",
        "lastAccessed": "2024-10-08T03:03:11.861Z"
    },
    {
        "key": "m_pixel_ratio",
        "value": "2",
        "domain": "facebook.com",
        "path": "/",
        "hostOnly": false,
        "creation": "2024-10-08T03:03:11.861Z",
        "lastAccessed": "2024-10-08T03:03:11.861Z"
    },
    {
        "key": "wd",
        "value": "360x694",
        "domain": "facebook.com",
        "path": "/",
        "hostOnly": false,
        "creation": "2024-10-08T03:03:11.861Z",
        "lastAccessed": "2024-10-08T03:03:11.861Z"
    },
    {
        "key": "c_user",
        "value": "61566637599017",
        "domain": "facebook.com",
        "path": "/",
        "hostOnly": false,
        "creation": "2024-10-08T03:03:11.861Z",
        "lastAccessed": "2024-10-08T03:03:11.861Z"
    },
    {
        "key": "fr",
        "value": "0uK2tJF1Uria7PxbT.AWWMsLdSTnkXDl0auEfaYMX32oU.BnA-jg..AAA.0.0.BnBKDs.AWWcjVMQgHY",
        "domain": "facebook.com",
        "path": "/",
        "hostOnly": false,
        "creation": "2024-10-08T03:03:11.861Z",
        "lastAccessed": "2024-10-08T03:03:11.861Z"
    },
    {
        "key": "xs",
        "value": "18%3ATCySn2tKw-3VFA%3A2%3A1728356588%3A-1%3A-1",
        "domain": "facebook.com",
        "path": "/",
        "hostOnly": false,
        "creation": "2024-10-08T03:03:11.861Z",
        "lastAccessed": "2024-10-08T03:03:11.861Z"
    },
    {
        "key": "locale",
        "value": "en_GB",
        "domain": "facebook.com",
        "path": "/",
        "hostOnly": false,
        "creation": "2024-10-08T03:03:11.861Z",
        "lastAccessed": "2024-10-08T03:03:11.861Z"
    },
    {
        "key": "m_page_voice",
        "value": "61566637599017",
        "domain": "facebook.com",
        "path": "/",
        "hostOnly": false,
        "creation": "2024-10-08T03:03:11.861Z",
        "lastAccessed": "2024-10-08T03:03:11.861Z"
    },
    {
        "key": "fbl_st",
        "value": "101626224%3BT%3A28805943",
        "domain": "facebook.com",
        "path": "/",
        "hostOnly": false,
        "creation": "2024-10-08T03:03:11.861Z",
        "lastAccessed": "2024-10-08T03:03:11.861Z"
    },
    {
        "key": "wl_cbv",
        "value": "v2%3Bclient_version%3A2642%3Btimestamp%3A1728356591",
        "domain": "facebook.com",
        "path": "/",
        "hostOnly": false,
        "creation": "2024-10-08T03:03:11.861Z",
        "lastAccessed": "2024-10-08T03:03:11.861Z"
    }
]
